{
  "project_info": {
    "project_number": "948649487918",
    "project_id": "mybody-7f292",
    "storage_bucket": "mybody-7f292.appspot.com"
  },
  "client": [
    {
      "client_info": {
        "mobilesdk_app_id": "1:948649487918:android:de0cebde0be1ebde44f9bf",
        "android_client_info": {
          "package_name": "com.example.mybody"
        }
      },
      "oauth_client": [
        {
          "client_id": "948649487918-u6bpflc832qqtqn9cere7g5mu1q52m26.apps.googleusercontent.com",
          "client_type": 3
        }
      ],
      "api_key": [
        {
          "current_key": "AIzaSyDMQ-RZnln9PLMYUTGbGG_ipcw2aCHA6Ek"
        }
      ],
      "services": {
        "appinvite_service": {
          "other_platform_oauth_client": [
            {
              "client_id": "948649487918-u6bpflc832qqtqn9cere7g5mu1q52m26.apps.googleusercontent.com",
              "client_type": 3
            }
          ]
        }
      }
    }
  ],
  "configuration_version": "1"
}